artless.py
artless_framework-0.1.4.dist-info/LICENSE
artless_framework-0.1.4.dist-info/METADATA
artless_framework-0.1.4.dist-info/WHEEL
artless_framework-0.1.4.dist-info/top_level.txt
artless_framework-0.1.4.dist-info/RECORD
